_pysysdc.cpython-36m-x86_64-linux-gnu.so
pysysdc-2.0.8.data/scripts/dcbus
pysysdc.libs/liblzma-9c0610aa.so.5.2.2
pysysdc.libs/libsystemd-2f543c46.so.0.17.0
pysysdc.libs/liblz4-b5d80b8d.so.1.7.1
pysysdc.libs/libselinux-3f284c04.so.1
pysysdc.libs/libpcre-8e472c69.so.3.13.3
pysysdc.libs/libgcrypt-0005395c.so.20.1.6
pysysdc.libs/libgpg-error-24781f22.so.0.21.0
pysysdc/signals.h
pysysdc/unit.py
pysysdc/sd_python_runner.h
pysysdc/pysysdc.c
pysysdc/variant.c
pysysdc/systemd_methods.h
pysysdc/sdbus.c
pysysdc/python_runner.h
pysysdc/connect.c
pysysdc/sdbus.h
pysysdc/__init__.py
pysysdc/dc_error_handling.c
pysysdc/systemd_methods.c
pysysdc/variant.h
pysysdc/__version__.py
pysysdc/methods.py
pysysdc/signals.c
pysysdc/python_runner.c
pysysdc/dc_error_handling.h
pysysdc/sdreply.py
pysysdc/debug.h
pysysdc/sd_python_runner.c
pysysdc/helpers.h
pysysdc/systemctl.py
pysysdc/connect.h
pysysdc/sdbus.py
pysysdc/helpers.c
etc/dbus-1/system-local.conf
pysysdc-2.0.8.dist-info/top_level.txt
pysysdc-2.0.8.dist-info/LICENSE
pysysdc-2.0.8.dist-info/WHEEL
pysysdc-2.0.8.dist-info/RECORD
pysysdc-2.0.8.dist-info/METADATA
