Metadata-Version: 2.1
Name: pysysdc
Version: 2.0.8
Summary: Python C library for SD-Bus communication
Home-page: https://github.com/sb0y/pysysdc
Author: Andrey Bagrintsev, Anatolii Cheban, Oleksandr Avdieiev
Author-email: andrey@bagrintsev.me, 1timkill@gmail.com, avdieev@gmail.com
Maintainer: Andrey Bagrintsev
Maintainer-email: andrey@bagrintsev.me
License: BSD
Platform: UNKNOWN
Classifier: Intended Audience :: Developers
Classifier: Topic :: Software Development :: Libraries :: Python Modules
Classifier: License :: OSI Approved :: GNU General Public License (GPL)
Classifier: Development Status :: 5 - Production/Stable
Classifier: Operating System :: Unix
Classifier: Programming Language :: C
License-File: LICENSE
